[
  {
    "id": "CV0901",
    "level": 2,
    "level_name": {
      "local": "Freguesia",
      "en": "Parish"
    },
    "name": {
      "local": "Nossa Senhora do Livramento",
      "en": "Nossa Senhora do Livramento",
      "slug": "nossa-senhora-do-livramento-cv0901"
    },
    "code": {
      "id": "CV0901",
      "iso": null
    },
    "parent": {
      "id": "CV09",
      "level": 1,
      "name": {
        "local": "Ribeira Grande",
        "en": "Ribeira Grande",
        "slug": "ribeira-grande-cv09"
      }
    },
    "ancestors": [
      {
        "id": "CV09",
        "level": 1,
        "name": {
          "local": "Ribeira Grande",
          "en": "Ribeira Grande",
          "slug": "ribeira-grande-cv09"
        }
      }
    ],
    "children_count": {},
    "zip_codes": [],
    "geo": {
      "lat": "17.182",
      "lon": "-25.115"
    },
    "metadata": {},
    "source": {}
  },
  {
    "id": "CV0902",
    "level": 2,
    "level_name": {
      "local": "Freguesia",
      "en": "Parish"
    },
    "name": {
      "local": "Nossa Senhora do Rosario",
      "en": "Nossa Senhora do Rosario",
      "slug": "nossa-senhora-do-rosario-cv0902"
    },
    "code": {
      "id": "CV0902",
      "iso": null
    },
    "parent": {
      "id": "CV09",
      "level": 1,
      "name": {
        "local": "Ribeira Grande",
        "en": "Ribeira Grande",
        "slug": "ribeira-grande-cv09"
      }
    },
    "ancestors": [
      {
        "id": "CV09",
        "level": 1,
        "name": {
          "local": "Ribeira Grande",
          "en": "Ribeira Grande",
          "slug": "ribeira-grande-cv09"
        }
      }
    ],
    "children_count": {},
    "zip_codes": [],
    "geo": {
      "lat": "17.15",
      "lon": "-25.059"
    },
    "metadata": {},
    "source": {}
  },
  {
    "id": "CV0903",
    "level": 2,
    "level_name": {
      "local": "Freguesia",
      "en": "Parish"
    },
    "name": {
      "local": "Santo Crucifixo",
      "en": "Santo Crucifixo",
      "slug": "santo-crucifixo-cv0903"
    },
    "code": {
      "id": "CV0903",
      "iso": null
    },
    "parent": {
      "id": "CV09",
      "level": 1,
      "name": {
        "local": "Ribeira Grande",
        "en": "Ribeira Grande",
        "slug": "ribeira-grande-cv09"
      }
    },
    "ancestors": [
      {
        "id": "CV09",
        "level": 1,
        "name": {
          "local": "Ribeira Grande",
          "en": "Ribeira Grande",
          "slug": "ribeira-grande-cv09"
        }
      }
    ],
    "children_count": {},
    "zip_codes": [],
    "geo": {
      "lat": "17.131",
      "lon": "-25.112"
    },
    "metadata": {},
    "source": {}
  },
  {
    "id": "CV0904",
    "level": 2,
    "level_name": {
      "local": "Freguesia",
      "en": "Parish"
    },
    "name": {
      "local": "Sao Pedro Apostolo",
      "en": "Sao Pedro Apostolo",
      "slug": "sao-pedro-apostolo-cv0904"
    },
    "code": {
      "id": "CV0904",
      "iso": null
    },
    "parent": {
      "id": "CV09",
      "level": 1,
      "name": {
        "local": "Ribeira Grande",
        "en": "Ribeira Grande",
        "slug": "ribeira-grande-cv09"
      }
    },
    "ancestors": [
      {
        "id": "CV09",
        "level": 1,
        "name": {
          "local": "Ribeira Grande",
          "en": "Ribeira Grande",
          "slug": "ribeira-grande-cv09"
        }
      }
    ],
    "children_count": {},
    "zip_codes": [],
    "geo": {
      "lat": "17.13",
      "lon": "-25.186"
    },
    "metadata": {},
    "source": {}
  }
]